LICENSE
minecraft_object_utils/__init__.py
minecraft_object_utils/base_factory.py
minecraft_object_utils/data/minecraft-1.20-block.toml
minecraft_object_utils/data/minecraft-1.20-enchantment.toml
minecraft_object_utils/data/minecraft-1.20-entity.toml
minecraft_object_utils/data/minecraft-1.20-item.toml
minecraft_object_utils/minecraft_object_factory.py
minecraft_object_utils/mod_info.py
minecraft_object_utils/objects/base_object.py
minecraft_object_utils/objects/block.py
minecraft_object_utils/objects/block_state/constants.py
minecraft_object_utils/objects/block_state/transformations.py
minecraft_object_utils/objects/enchantment.py
minecraft_object_utils/objects/entity.py
minecraft_object_utils/objects/inventory.py
minecraft_object_utils/objects/item.py
minecraft_object_utils-0.5.0.dist-info/LICENSE
minecraft_object_utils-0.5.0.dist-info/METADATA
minecraft_object_utils-0.5.0.dist-info/WHEEL
minecraft_object_utils-0.5.0.dist-info/RECORD
