Metadata-Version: 2.1
Name: minecraft-object-utils
Version: 0.5.0
Summary: Create python objects that represent Minecraft blocks, items, and entities.
Home-page: https://github.com/BenBenBenB/minecraft-object-utils
License: MIT
Keywords: minecraft
Author: Ben Burton
Author-email: benjaminburtondev@gmail.com
Requires-Python: >=3.8,<4.0
Classifier: Development Status :: 3 - Alpha
Classifier: Intended Audience :: Developers
Classifier: License :: OSI Approved :: MIT License
Classifier: Operating System :: OS Independent
Classifier: Programming Language :: Python
Classifier: Programming Language :: Python :: 3
Classifier: Programming Language :: Python :: 3.8
Classifier: Programming Language :: Python :: 3.9
Classifier: Programming Language :: Python :: 3.10
Classifier: Programming Language :: Python :: 3.11
Classifier: Topic :: Games/Entertainment
Classifier: Topic :: Software Development :: Libraries :: Python Modules
Requires-Dist: strenum (>=0.4.15,<0.5.0)
Requires-Dist: toml (>=0.10.0,<0.11.0)
Project-URL: Repository, https://github.com/BenBenBenB/minecraft-object-utils
